tacobox
