Metadata-Version: 2.1
Name: taco-box
Version: 0.1.1
Summary: An implementation library of Tiling and Corruption (TACo) Augmentations for OCR/HTR!
Home-page: https://github.com/kartikgill/taco-box
Author: Kartik Chaudhary
Author-email: kartikgill96@gmail.com
License: UNKNOWN
Platform: UNKNOWN
Classifier: Programming Language :: Python :: 3.7
Classifier: License :: OSI Approved :: Apache Software License
